lykos/__init__.py
lykos/cli.py
lykos/confidence.py
lykos/git_secrets_cleaner.py
lykos/main.py
lykos/patterns.py
lykos/pre_commit_guard.py
lykos/secret_guardian.py
lykos/secret_scanner.py
lykos/secret_utils.py
test/__init__.py
test/test_cli.py
test/test_confidence.py
test/test_git_secrets_cleaner.py
test/test_pre_commit_guard.py
test/test_secret_guardian.py
test/test_secret_scanner.py
lykos-0.0.1.dist-info/METADATA
lykos-0.0.1.dist-info/WHEEL
lykos-0.0.1.dist-info/entry_points.txt
lykos-0.0.1.dist-info/top_level.txt
lykos-0.0.1.dist-info/RECORD
